pytest_trace/__init__.py
pytest_trace/plugin.py
pytest_trace-1.0.0.dist-info/METADATA
pytest_trace-1.0.0.dist-info/WHEEL
pytest_trace-1.0.0.dist-info/entry_points.txt
pytest_trace-1.0.0.dist-info/top_level.txt
pytest_trace-1.0.0.dist-info/RECORD
